rtl/alu_32bit_parameterized.v
`timescale 1ns / 1ps
//////////////////////////////////////////////////////////////////////////////////
// Company: 
// Engineer: 
// 
// Create Date: 07/02/2026 07:13:05 PM
// Design Name: 
// Module Name: parameterized_alu_32_bit
// Project Name: 
// Target Devices: 
// Tool Versions: 
// Description: 
// 
// Dependencies: 
// 
// Revision:
// Revision 0.01 - File Created
// Additional Comments:
// 
//////////////////////////////////////////////////////////////////////////////////


module parameterized_alu_32_bit #(
parameter WIDTH = 32)(
input [WIDTH-1:0] A,
input [WIDTH-1:0] B,
input [3:0] opcode,

output reg[WIDTH-1:0] Result,
output reg Zero,
output reg Carry,
output reg Overflow,
output reg Negative

    );

always @(*) 
begin
Result = 0;
Zero = 0 ;
Carry = 0;
Overflow = 0;
Negative = 0;

case (opcode)
    4'b0000 : begin
    {Carry , Result} = A + B ;
    
    Overflow = (A[WIDTH-1] == B[WIDTH-1]) &&
                   (Result[WIDTH-1] != A[WIDTH-1]);
    end
    
    4'b0001 : begin
    {Carry , Result} = A - B ;
    
    Overflow = (A[WIDTH-1] != B[WIDTH-1]) &&
                   (Result[WIDTH-1] != A[WIDTH-1]);
    end
    
    4'b0010 : begin
    Result = A & B ;
    end
    
    4'b0011 : begin
    Result = A | B ;
    end
    
    4'b0100 : begin
    Result = A ^ B ;
    end

    4'b0101 : begin
    Result = ~A;
    end

    4'b0110 : begin
    Result = ~(A & B);
    end

    4'b0111 : begin
    Result = ~(A | B);
    end
    
    4'b1000 : begin
    Result = ~(A ^ B);
    end
    
    4'b1001 : begin
    if ($signed(A) < $signed(B))
        Result = 1;
    else
        Result = 0;
    end
    
    4'b1010 : begin
        Result = A << B[4:0];
    end
    
    4'b1011 : begin
        Result = A >> B[4:0];
    end
    
    4'b1100 : begin
        Result = $signed(A) >>> B[4:0];
    end
    
    default : begin
    Result = 0;
    end
    
endcase
    Zero = (Result == 0);
    Negative = Result[WIDTH-1];
end
   
endmodule

testbench/alu_32bit_parameterized_tb.v
`timescale 1ns / 1ps
//////////////////////////////////////////////////////////////////////////////////
// Company: 
// Engineer: 
// 
// Create Date: 07/02/2026 07:50:41 PM
// Design Name: 
// Module Name: parameterized_alu_32_bit_tb
// Project Name: 
// Target Devices: 
// Tool Versions: 
// Description: 
// 
// Dependencies: 
// 
// Revision:
// Revision 0.01 - File Created
// Additional Comments:
// 
//////////////////////////////////////////////////////////////////////////////////


module parameterized_alu_32_bit_tb ;
parameter WIDTH = 32 ;

reg [WIDTH-1:0] A ; 
reg [WIDTH-1:0] B ;
reg [3:0] opcode ;
wire [WIDTH-1:0] Result ; 
wire Zero ;
wire Carry ;
wire Overflow ;
wire Negative ;
parameterized_alu_32_bit #(.WIDTH(WIDTH)) uut(.A(A) , .B(B) , .opcode(opcode) , .Result(Result) , .Zero(Zero) , .Carry(Carry) , .Overflow(Overflow) , .Negative(Negative));
integer j ;
initial 
begin
$dumpfile("parameterized_alu_32_bit.vcd");
$dumpvars(0, parameterized_alu_32_bit_tb);

$monitor($time, 
                "A = %b , B = %b , opcode = %b , Result = %b , Zero = %b , Carry = %b , Overflow = %b , Negative = %b",
                A,B,opcode,Result,Zero,Carry,Overflow,Negative);

A = 32'd10;
B = 32'd20;
opcode = 4'b0000;
#10;  

A = 32'h7FFFFFFF;
B = 32'h00000001;
opcode = 4'b0000;
#10;

A = 32'd20;
B = 32'd5;
opcode = 4'b0001;
#10;  

A = 32'hF0F0F0F0;
B = 32'h0F0F0F0F;
opcode = 4'b0010;
#10;   

A = 32'hF0F0F0F0;
B = 32'h0F0F0F0F;
opcode = 4'b0011;
#10; 
 
A = 32'd10;
B = 32'd10;
opcode = 4'b0001; 
#10;

A = 32'd5;
B = 32'd10;
opcode = 4'b0001; 
#10;

A = 32'hFFFFFFFF;
B = 32'h00000001;
opcode = 4'b0000;
#10;

A = 32'hAAAA5555;
B = 32'h5555AAAA;
opcode = 4'b0100;
#10;

A = 32'h0000FFFF;
B = 32'd0;
opcode = 4'b0101;
#10;

A = 32'hFFFFFFFF;
B = 32'h00000000;
opcode = 4'b0110;
#10;

A = 32'h00000000;
B = 32'h00000000;
opcode = 4'b0111;
#10;

A = 32'hAAAAAAAA;
B = 32'hAAAAAAAA;
opcode = 4'b1000;
#10;

A = 32'd5;
B = 32'd10;
opcode = 4'b1001;
#10;

A = 32'd5;
B = 32'd2;
opcode = 4'b1010;
#10;

A = 32'd16;
B = 32'd2;
opcode = 4'b1011;
#10;

A = -32'd16;
B = 32'd2;
opcode = 4'b1100;
#10;

$finish ;

end

endmodule

simulation/parameterized_alu_32_bit.vcd
$date
	Wed Jul 15 15:41:30 2026
$end
$version
	Icarus Verilog
$end
$timescale
	1ps
$end
$scope module parameterized_alu_32_bit_tb $end
$var wire 1 ! Zero $end
$var wire 32 " Result [31:0] $end
$var wire 1 # Overflow $end
$var wire 1 $ Negative $end
$var wire 1 % Carry $end
$var parameter 32 & WIDTH $end
$var reg 32 ' A [31:0] $end
$var reg 32 ( B [31:0] $end
$var reg 4 ) opcode [3:0] $end
$scope module uut $end
$var wire 32 * A [31:0] $end
$var wire 32 + B [31:0] $end
$var wire 4 , opcode [3:0] $end
$var parameter 32 - WIDTH $end
$var reg 1 % Carry $end
$var reg 1 $ Negative $end
$var reg 1 # Overflow $end
$var reg 32 . Result [31:0] $end
$var reg 1 ! Zero $end
$upscope $end
$upscope $end
$enddefinitions $end
$comment Show the parameter values. $end
$dumpall
b100000 -
b100000 &
$end
#0
$dumpvars
b11110 .
b0 ,
b10100 +
b1010 *
b0 )
b10100 (
b1010 '
0%
0$
0#
b11110 "
0!
$end
#10000
1$
1#
b10000000000000000000000000000000 "
b10000000000000000000000000000000 .
b1 (
b1 +
b1111111111111111111111111111111 '
b1111111111111111111111111111111 *
#20000
0$
0#
b1111 "
b1111 .
b1 )
b1 ,
b101 (
b101 +
b10100 '
b10100 *
#30000
1!
b0 "
b0 .
b10 )
b10 ,
b1111000011110000111100001111 (
b1111000011110000111100001111 +
b11110000111100001111000011110000 '
b11110000111100001111000011110000 *
#40000
1$
b11111111111111111111111111111111 "
b11111111111111111111111111111111 .
0!
b11 )
b11 ,
#50000
1!
0$
b0 "
b0 .
b1 )
b1 ,
b1010 (
b1010 +
b1010 '
b1010 *
#60000
1$
1%
b11111111111111111111111111111011 "
b11111111111111111111111111111011 .
0!
b101 '
b101 *
#70000
1!
0$
1%
b0 "
b0 .
b0 )
b0 ,
b1 (
b1 +
b11111111111111111111111111111111 '
b11111111111111111111111111111111 *
#80000
1$
b11111111111111111111111111111111 "
b11111111111111111111111111111111 .
0%
0!
b100 )
b100 ,
b1010101010101011010101010101010 (
b1010101010101011010101010101010 +
b10101010101010100101010101010101 '
b10101010101010100101010101010101 *
#90000
1$
b11111111111111110000000000000000 "
b11111111111111110000000000000000 .
b101 )
b101 ,
b0 (
b0 +
b1111111111111111 '
b1111111111111111 *
#100000
1$
b11111111111111111111111111111111 "
b11111111111111111111111111111111 .
b110 )
b110 ,
b11111111111111111111111111111111 '
b11111111111111111111111111111111 *
#110000
1$
b11111111111111111111111111111111 "
b11111111111111111111111111111111 .
b111 )
b111 ,
b0 '
b0 *
#120000
1$
b11111111111111111111111111111111 "
b11111111111111111111111111111111 .
b1000 )
b1000 ,
b10101010101010101010101010101010 (
b10101010101010101010101010101010 +
b10101010101010101010101010101010 '
b10101010101010101010101010101010 *
#130000
0$
b1 "
b1 .
b1001 )
b1001 ,
b1010 (
b1010 +
b101 '
b101 *
#140000
b10100 "
b10100 .
b1010 )
b1010 ,
b10 (
b10 +
#150000
b100 "
b100 .
b1011 )
b1011 ,
b10000 '
b10000 *
#160000
1$
b11111111111111111111111111111100 "
b11111111111111111111111111111100 .
b1100 )
b1100 ,
b11111111111111111111111111110000 '
b11111111111111111111111111110000 *
